tomillo/__init__.py
tomillo/_version.py
tomillo/core.py
tomillo/exception.py
tomillo/log_prep.py
tomillo/misc.py
tomillo/mock.py
tomillo/singleton.py
tomillo-0.3.5.dist-info/LICENSE
tomillo-0.3.5.dist-info/METADATA
tomillo-0.3.5.dist-info/WHEEL
tomillo-0.3.5.dist-info/top_level.txt
tomillo-0.3.5.dist-info/RECORD
