Metadata-Version: 2.1
Name: tomillo
Version: 0.3.5
Summary: Configuration system.
Author-email: bashiron <bioshiron@gmail.com>
Project-URL: Homepage, https://github.com/bashiron/tomillo
Project-URL: Issues, https://github.com/bashiron/tomillo/issues
Classifier: Development Status :: 3 - Alpha
Classifier: License :: OSI Approved :: GNU General Public License v3 (GPLv3)
Classifier: Operating System :: POSIX :: Linux
Classifier: Programming Language :: Python :: 3.12
Classifier: Topic :: Software Development :: Libraries
Classifier: Intended Audience :: Developers
Requires-Python: >=3.12
License-File: LICENSE
Requires-Dist: loguru ==0.7.3
Requires-Dist: tomlkit ==0.13.2
